<annotation>
	<folder>images</folder>
	<filename>ch16_2019030220141220.jpg</filename>
	<path>C:\Users\寒杰\OneDrive\桌面\yolov5-master\VOCDATA\images\ch16_2019030220141220.jpg</path>
	<source>
		<database>Unknown</database>
	</source>
	<size>
		<width>2048</width>
		<height>1536</height>
		<depth>3</depth>
	</size>
	<segmented>0</segmented>
	<object>
		<name>car</name>
		<pose>Unspecified</pose>
		<truncated>0</truncated>
		<difficult>0</difficult>
		<bndbox>
			<xmin>249</xmin>
			<ymin>274</ymin>
			<xmax>570</xmax>
			<ymax>523</ymax>
		</bndbox>
	</object>
	<object>
		<name>people</name>
		<pose>Unspecified</pose>
		<truncated>0</truncated>
		<difficult>0</difficult>
		<bndbox>
			<xmin>817</xmin>
			<ymin>413</ymin>
			<xmax>910</xmax>
			<ymax>693</ymax>
		</bndbox>
	</object>
	<object>
		<name>people</name>
		<pose>Unspecified</pose>
		<truncated>0</truncated>
		<difficult>0</difficult>
		<bndbox>
			<xmin>1020</xmin>
			<ymin>195</ymin>
			<xmax>1134</xmax>
			<ymax>324</ymax>
		</bndbox>
	</object>
	<object>
		<name>people</name>
		<pose>Unspecified</pose>
		<truncated>0</truncated>
		<difficult>0</difficult>
		<bndbox>
			<xmin>1092</xmin>
			<ymin>258</ymin>
			<xmax>1145</xmax>
			<ymax>447</ymax>
		</bndbox>
	</object>
	<object>
		<name>people</name>
		<pose>Unspecified</pose>
		<truncated>0</truncated>
		<difficult>0</difficult>
		<bndbox>
			<xmin>1743</xmin>
			<ymin>134</ymin>
			<xmax>1785</xmax>
			<ymax>262</ymax>
		</bndbox>
	</object>
	<object>
		<name>car</name>
		<pose>Unspecified</pose>
		<truncated>0</truncated>
		<difficult>0</difficult>
		<bndbox>
			<xmin>1107</xmin>
			<ymin>247</ymin>
			<xmax>1424</xmax>
			<ymax>518</ymax>
		</bndbox>
	</object>
</annotation>
